influxpy
