Metadata-Version: 1.1
Name: influxpy
Version: 0.2.1
Summary: Python logging handler for sending messages to InfluxDB using the line protocol over UDP.
Home-page: https://github.com/awelzel/influxpy
Author: Arne Welzel
Author-email: arne.welzel@gmail.com
License: BSD License
Keywords: influxdb grafana logger logging udp
Platform: UNKNOWN
Classifier: License :: OSI Approved :: BSD License
Classifier: Programming Language :: Python :: 2
Classifier: Programming Language :: Python :: 3
